unoff_qweather_mcp/__init__.py
unoff_qweather_mcp/__main__.py
unoff_qweather_mcp/params.py
unoff_qweather_mcp/qweather.py
unoff_qweather_mcp-0.1.4.dist-info/licenses/LICENSE
unoff_qweather_mcp-0.1.4.dist-info/METADATA
unoff_qweather_mcp-0.1.4.dist-info/WHEEL
unoff_qweather_mcp-0.1.4.dist-info/entry_points.txt
unoff_qweather_mcp-0.1.4.dist-info/top_level.txt
unoff_qweather_mcp-0.1.4.dist-info/RECORD
