Metadata-Version: 2.4
Name: unoff-qweather-mcp
Version: 0.1.4
Summary: An unofficial MCP (Multiagent Conversation Protocol) wrapper for the QWeather API
Requires-Python: >=3.10
License-File: LICENSE
Requires-Dist: httpx>=0.21.0
Requires-Dist: mcp>=1.7.0
Dynamic: license-file
